topsis_shubhkaram_102303303/_init_.py
topsis_shubhkaram_102303303/topsis.py
topsis_shubhkaram_102303303-1.0.3.dist-info/METADATA
topsis_shubhkaram_102303303-1.0.3.dist-info/WHEEL
topsis_shubhkaram_102303303-1.0.3.dist-info/entry_points.txt
topsis_shubhkaram_102303303-1.0.3.dist-info/top_level.txt
topsis_shubhkaram_102303303-1.0.3.dist-info/RECORD
