Metadata-Version: 2.4
Name: Topsis-Shubhkaram-102303303
Version: 1.0.3
Summary: A Python package for TOPSIS multi-criteria decision making
Author: Shubhkaram Singh
Author-email: YOUR_EMAIL@gmail.com
Requires-Dist: numpy
Requires-Dist: pandas
Dynamic: author
Dynamic: author-email
Dynamic: description
Dynamic: description-content-type
Dynamic: requires-dist
Dynamic: summary
